[
  {
    "userId": 1,
    "name": "Bruce Wayne",
    "username": "batman",
    "email": "bruce@gmail.com",
    "password": "catwoman",
    "score": 45,
    "completedCourseId": [3, 4, 2],
    "completedCourses": [
      {
        "name": "HTML for beginners",
        "courseId": 1,
        "score": 12,
        "completed": true
      },
      {
        "name": "CSS Gridd",
        "courseId": 2,
        "score": 18,
        "completed": true
      },
      {
        "name": "CSS Display",
        "courseId": 3,
        "score": 12,
        "completed": false
      },
      {
        "name": "CSS Positions",
        "courseId": 5,
        "score": 8,
        "completed": false
      }
    ]
  },
  {
    "userId": 2,
    "name": "Barry Alan",
    "username": "flash",
    "email": "barry@gmail.com",
    "password": "iris",
    "completedCourseId": [1, 2, 3],
    "completedCourses": [
      {
        "name": "HTML for beginners",
        "courseId": 1,
        "score": 10,
        "completed": true
      },
      {
        "name": "CSS Gridd",
        "courseId": 2,
        "score": 6,
        "completed": true
      },
      {
        "name": "CSS Display",
        "courseId": 3,
        "score": 5,
        "completed": false
      }
    ]
  },
  {
    "userId": 3,
    "name": "Oliver Queen",
    "username": "arrow",
    "email": "oliver@gmail.com",
    "password": "canary",
    "score": 15,
    "completedCourseId": [3, 4, 5],
    "completedCourses": [
      {
        "name": "HTML for beginners",
        "courseId": 3,
        "score": 12,
        "completed": true
      },
      {
        "name": "CSS Gridd",
        "courseId": 4,
        "score": 18,
        "completed": true
      },
      {
        "name": "CSS Display",
        "courseId": 5,
        "score": 12,
        "completed": false
      }
    ]
  }
]
